<annotation>
	<folder>Train</folder>
	<filename>kangkung (17).jpg</filename>
	<path>C:\Users\riandra putra\Downloads\labelImg-master\labelImg-master\bangkitdata\Train\kangkung (17).jpg</path>
	<source>
		<database>Unknown</database>
	</source>
	<size>
		<width>487</width>
		<height>413</height>
		<depth>3</depth>
	</size>
	<segmented>0</segmented>
	<object>
		<name>Kangkung</name>
		<pose>Unspecified</pose>
		<truncated>0</truncated>
		<difficult>0</difficult>
		<bndbox>
			<xmin>55</xmin>
			<ymin>28</ymin>
			<xmax>467</xmax>
			<ymax>401</ymax>
		</bndbox>
	</object>
</annotation>
